adf2stowf/__init__.py
adf2stowf/adf2stowf.py
adf2stowf/adfread.py
adf2stowf/cli_main.py
adf2stowf/stowfn.py
adf2stowf-0.9.1.dist-info/METADATA
adf2stowf-0.9.1.dist-info/WHEEL
adf2stowf-0.9.1.dist-info/entry_points.txt
adf2stowf-0.9.1.dist-info/top_level.txt
adf2stowf-0.9.1.dist-info/RECORD
