Metadata-Version: 2.4
Name: adf2stowf
Version: 0.9.1
Summary: Converter from ADF TAPE21.asc to CASINO stowfn.data
Author-email: Vladimir Konkov <Konjkov.VV@gmail.com>
Maintainer-email: Vladimir Konkov <Konjkov.VV@gmail.com>
Project-URL: repository, https://github.com/Konjkov/adf2stowf/tree/original
Classifier: Development Status :: 5 - Production/Stable
Classifier: Environment :: Console
Classifier: Intended Audience :: Science/Research
Classifier: Operating System :: POSIX :: Linux
Classifier: Topic :: Scientific/Engineering :: Chemistry
Classifier: Programming Language :: Python :: 3.9
Requires-Python: <3.10,>=3.9
Requires-Dist: numpy==1.24.4
Requires-Dist: scipy-weave==0.19.0
Requires-Dist: matplotlib>=3.9.0
